{
    "descriptions": [
        "먹을 것이 있는 곳이라면\n어디서든 서식한다.\n온종일 먹이를 찾아다닌다.",
        "송곳니는 길고 날카롭다.\n평생 자라나기 때문에\n단단한 것을 갉아서 깎는다.",
        "경계심이 매우 강해서 자고 있을 때도\n귀를 움직여 주변의 소리를 듣고 있다.\n어디에든 자리를 잡고 둥지를 만든다.",
        "경계심이 매우 강해서 자고 있을 때도\n귀를 움직여 주변의 소리를 듣고 있다.\n어디에든 자리를 잡고 둥지를 만든다.",
        "2개의 이빨로 뭐든지 일단\n갉고 본다. 1마리를 발견했다면\n그곳에 40마리는 살고 있을 것이다.",
        "앞니는 죽을 때까지 계속 자라기 때문에\n관리가 필요하다. 이갈이 용품을\n준비하지 않으면 기둥을 갉는다.",
        "생명력이 강해서 더러운\n곳에서도 사는데 문제없다.\n내버려두면 점점 수가 불어난다.",
        "평생 앞니가 계속 자란다.\n너무 많이 자라면 먹이를\n먹을 수 없어 굶어 죽는다.",
        "흔한 포켓몬이지만 주의해야 한다.\n날카로운 앞니는 단단한 나무도\n간단하게 부러뜨린다.",
        "2개의 이빨로 뭐든지 일단\n갉고 본다. 1마리를 발견했다면\n그곳에 40마리는 살고 있을 것이다."
    ],
    "height": 0.3,
    "id": 19,
    "image_url": "https://raw.githubusercontent.com/PokeAPI/sprites/master/sprites/pokemon/other/official-artwork/19.png",
    "name": "꼬렛",
    "types": [
        "노말"
    ],
    "weight": 3.5
}