{
    "descriptions": [
        "점점 자라면서 다시 돋아나는\n머리의 끝이 아름다워\n보물로서 인기가 많다.",
        "남쪽의 깨끗한 바다를 좋아한다.\n더러운 바다면 산호 가지는\n색이 거무스레해지고 엉망이 된다.",
        "산호 가지는 태양의 빛을 받으면\n일곱 빛깔로 반짝반짝 빛이 나 정말 아름답다.\n부러져도 하룻밤이면 원래대로 자라난다.",
        "따뜻한 바다에 모인 코산호는\n작은 포켓몬들의 은신처가 된다.\n수온이 낮아지면 남쪽으로 이동한다.",
        "산호 가지가 머리에 자란다.\n꽤 간단히 부러지지만\n사흘 정도면 원래대로 돌아온다.",
        "머리의 가지를 노리고 시마사리가\n쫓아오면 자신의 가지를\n뚝 부러뜨리고 도망친다.",
        "알로라에 사는 코산호는\n핑크가 매우 선명하고 짙다.\n영양이 풍부한 바다 덕분이다.",
        "천적인 시마사리가 잔뜩 있는\n알로라에서는 머리의 가지가\n짧은 코산호가 많다.",
        "머리에 난 가지는 부러져도\n다시 자란다. 예쁜 것은\n순산을 기원하는 부적으로 쓰인다.",
        "따뜻한 바다에 서식한다.\n태고에는 가라르 근해에서도\n많은 수가 서식했었다."
    ],
    "height": 0.6,
    "image_url": "https://raw.githubusercontent.com/PokeAPI/sprites/master/sprites/pokemon/other/official-artwork/222.png",
    "name": "코산호",
    "types": [
        "물",
        "바위"
    ],
    "weight": 5.0
}