{
    "descriptions": [
        "체격은 작지만 괴력몬이나\n하리뭉 등의 커다란 포켓몬과\n막상막하로 싸우는 테크니션이다.",
        "날개를 사용해 공중에서\n자세를 컨트롤한다. 막기 어려운\n머리 위에서부터 공격해온다.",
        "체격은 작지만 괴력몬이나\n하리뭉 등의 커다란 포켓몬과\n막상막하로 싸우는 테크니션이다.",
        "날개를 사용해 공중에서\n자세를 컨트롤한다. 막기 어려운\n머리 위에서부터 공격해온다.",
        "빠른 기술로 상대를 압도한다.\n필살기를 쓰기 위한 어필이\n너무 길어서 위기에 처하기도 한다.",
        "경쾌한 점프로 상대의\n사각을 돌며 싸운다.\n화려한 관절 기술도 특기다.",
        "경쾌한 몸놀림을 활용한 전법으로\n상대의 체력을 빼앗은 뒤\n화려한 큰 기술을 먹인다.",
        "끝을 내는 결정적인 기술을 쓰기 전에\n반드시 포즈를 취한다.\n그 틈에 반격당하기도 한다."
    ],
    "height": 0.8,
    "image_url": "https://raw.githubusercontent.com/PokeAPI/sprites/master/sprites/pokemon/other/official-artwork/701.png",
    "name": "루차불",
    "types": [
        "격투",
        "비행"
    ],
    "weight": 21.5
}