{
    "descriptions": [
        "1초당 16번 나무를 쪼아서\n구멍을 낸다. 낸 구멍은 먹이를\n넣어두는 저장고나 둥지로 쓴다.",
        "나무열매가 먹이다. 먹고 남은\n씨앗은 총알처럼 입에서\n발사하여 공격에 사용한다.",
        "딱딱한 부리로 나무를 쫀다.\n쪼는 리듬으로 그때의 기분이나\n상태를 대강 알 수 있다.",
        "가늘어 보이지만 강인한\n목 근육을 가졌다. 초당\n16연타로 나무를 마구 쪼아 댄다."
    ],
    "height": 0.3,
    "id": 731,
    "image_url": "https://raw.githubusercontent.com/PokeAPI/sprites/master/sprites/pokemon/other/official-artwork/731.png",
    "name": "콕코구리",
    "types": [
        "노말",
        "비행"
    ],
    "weight": 1.2
}