{
    "descriptions": [
        "すこしの　しげきに　はんのうして\nばくはつする。バクダンボールという\nあだなで　こわがられて　いる。",
        "あふれるほどの　でんきエネルギーを\nたいないに　ためこんでいるので\nすこしの　しげきで　ばくはつする。",
        "くうきちゅうの　でんきエネルギーを　たべる。\nカミナリの　おちる　ひは　でんきを　たべすぎた\nマルマインが　あちらこちらで　だいばくはつする。",
        "でんきに　ひきよせられる　せいしつを　もつ。\nおもに　はつでんしょに　あつまってきて　つくった\nばかりの　でんきを　たべてしまう　こまりものだ。",
        "すこしでも　しょうげきを　あたえると\nたいないの　エレクトンエネルギーが\nあふれて　ばくはつ　してしまう。",
        "すこしでも　しょうげきを　あたえると\nたいないの　エレクトンエネルギーが\nあふれて　ばくはつ　してしまう。"
    ],
    "height": 1.2,
    "id": 101,
    "image_url": "https://raw.githubusercontent.com/PokeAPI/sprites/master/sprites/pokemon/other/official-artwork/101.png",
    "name": "マルマイン",
    "types": [
        "でんき"
    ],
    "weight": 66.6
}