{
    "descriptions": [
        "きの　かわを　かさねあわせて\nカラを　ぶあつくするのが　だいすき。\nおもくなっても　きにしない。",
        "きのみに　そっくり。まちがわれて\nとりポケモンに　つつかれてしまうが\nかたい　カラで　まもられている。",
        "きの　えだに　ぶらさがり　えものを　まっている。\nきを　ゆらされて　しょくじの　じゃまを　されると\nじめんに　おちてから　いきなり　ばくはつするぞ。",
        "きの　えだに　ぶらさがり　えものを　まっている。\nきを　ゆらされて　しょくじの　じゃまを　されると\nじめんに　おちてから　いきなり　ばくはつするぞ。",
        "きに　ぶらさがり　じっと　えものの\nむしポケモンが　くるのを　まっている。\nアローラでの　こうぶつは　アブリーだ。",
        "きのかわを　だえきで　はりあわせ\nあつく　おおきくしていく。　としおいた\nクヌギダマは　とてつもない　でかさ。"
    ],
    "height": 0.6,
    "image_url": "https://raw.githubusercontent.com/PokeAPI/sprites/master/sprites/pokemon/other/official-artwork/204.png",
    "name": "クヌギダマ",
    "types": [
        "むし"
    ],
    "weight": 7.2
}