{
    "descriptions": [
        "あまぐもを　せおっているので\nどんなときでも　かみなりを　だせる。\nかみなりとともに　おちてきたという。",
        "たいないで　うずまく　ちからを\nでんげきとして　だしながら　だいちを\nかけめぐる　あらあらしい　ポケモン。",
        "かみなりの　スピードを　やどした　ポケモン。\nその　とおぼえは　かみなりが　おちた　ときの\nように　くうきを　ふるわせ　だいちを　ゆるがす。",
        "かみなりの　スピードを　やどした　ポケモン。\nその　とおぼえは　かみなりが　おちた　ときの\nように　くうきを　ふるわせ　だいちを　ゆるがす。"
    ],
    "height": 1.9,
    "image_url": "https://raw.githubusercontent.com/PokeAPI/sprites/master/sprites/pokemon/other/official-artwork/243.png",
    "name": "ライコウ",
    "types": [
        "でんき"
    ],
    "weight": 178.0
}