{
    "descriptions": [
        "せかいじゅうを　かけめぐり\nよごれた　みずを　きよめている。\nきたかぜと　ともに　はしりさる。",
        "いっしゅんで　きたなく　にごった\nみずも　きよめる　ちからをもつ。\nきたかぜの　うまれかわり　という。",
        "わきみずの　やさしさを　やどした　ポケモン。\nすべる　ような　みのこなしで　だいちを　はしり\nにごった　みずを　きよめる　ちからを　もつ。",
        "わきみずの　やさしさを　やどした　ポケモン。\nすべる　ような　みのこなしで　だいちを　はしり\nにごった　みずを　きよめる　ちからを　もつ。"
    ],
    "height": 2.0,
    "id": 245,
    "image_url": "https://raw.githubusercontent.com/PokeAPI/sprites/master/sprites/pokemon/other/official-artwork/245.png",
    "name": "スイクン",
    "types": [
        "みず"
    ],
    "weight": 187.0
}