{
    "descriptions": [
        "たかい　ちのうを　もつ　ポケモン。\nうでを　おりたたんで　とべば\nジェットきを　おいこす　スピードだ。",
        "たかい　ちのうを　もち　にんげんの\nことばを　りかいする。あらそいを\nきらう　やさしい　ポケモンだ。",
        "みた　ものや　かんがえた　イメージを　あいてに\nえいぞうとして　みせる　のうりょくを　もつ。\nにんげんの　ことばを　りかいすることが　できる。",
        "やさしい　こころの　もちぬしにしか　なつかない。\nうでを　おりたたむと　くうきていこうが　へって\nジェットき　よりも　はやく　そらを　とべるぞ。"
    ],
    "height": 2.0,
    "id": 381,
    "image_url": "https://raw.githubusercontent.com/PokeAPI/sprites/master/sprites/pokemon/other/official-artwork/381.png",
    "name": "ラティオス",
    "types": [
        "ドラゴン",
        "エスパー"
    ],
    "weight": 60.0
}