{
    "descriptions": [
        "かんそうした　ばしょを　このむ。\nめ　から　みずを　だして　からだの\nすいぶんを　ちょうせつする。",
        "かんそうした　くうきを　このむ。\nすいぶんを　ちょうせつ　するときに\nだす　みずが　なみだに　みえる。",
        "かんそうした　ばしょを　このむ。\nめ　から　みずを　だして　からだの\nすいぶんを　ちょうせつする。",
        "かんそうした　くうきを　このむ。\nすいぶんを　ちょうせつ　するときに\nだす　みずが　なみだに　みえる。",
        "みずが　にがてで　かわいた　ばしょに\nすんでいる。　まわりに　みどりが\nすくないので　よく　めだつ。",
        "からだの　よけいな　すいぶんを　めから\nそとに　だす。　その　せいぶんは\nにんげんの　あせに　にている。",
        "ひとみから　すいぶんを　ほうしゅつ。\nないているように　みえるので　てきを\nゆだんさせる　こうかも　あるらしい。",
        "あまり　からだが　しめりすぎると\nしんでしまうので　あせの　ように\nめから　すいぶんを　だしている。",
        "あせと　なみだを　めから　ながす。\nあせは　ちょっぴり　しょっぱくて\nなみだは　ほんのり　にがい　あじだ。",
        "かんそうした　いわばに　くらす。\nみどりの　たまは　かわくほど\nツヤツヤと　にぶく　かがやく。"
    ],
    "height": 0.5,
    "image_url": "https://raw.githubusercontent.com/PokeAPI/sprites/master/sprites/pokemon/other/official-artwork/438.png",
    "name": "ウソハチ",
    "types": [
        "いわ"
    ],
    "weight": 15.0
}