{
    "descriptions": [
        "かいだ　ものを　うっとりさせる\nかおりを　からだから　ただよわせる。\nたべた　もので　かおりが　かわる。",
        "むかしの　きふじんたちは　こうすいの\nかわりに　このみの　かおりを　だす\nシュシュプを　つれていた。",
        "かいだ　ものを　うっとりさせる\nかおりを　からだから　ただよわせる。\nたべた　もので　かおりが　かわる。",
        "むかしの　きふじんたちは　こうすいの\nかわりに　このみの　かおりを　だす\nシュシュプを　つれていた。",
        "たいないの　においぶくろで　においを\nつくる　ポケモン。　えさが　かわると\nつくられる　においも　かわる。",
        "ひとを　みりょうする　かぐわしい\nにおいを　からだから　ただよわせる。\nこうきな　ふじんたちに　あいされた。"
    ],
    "height": 0.2,
    "image_url": "https://raw.githubusercontent.com/PokeAPI/sprites/master/sprites/pokemon/other/official-artwork/682.png",
    "name": "シュシュプ",
    "types": [
        "フェアリー"
    ],
    "weight": 0.5
}