{
    "descriptions": [
        "はっぱの　ぶぶんは　カッターになって\nあいてを　きりさく。くちからは\nなんでも　とかす　えきたいを　はく。",
        "まず　どくのこなを　はき　あいての\nうごきを　とめて　しまってから\nようかいえきで　とどめを　さす。",
        "よるに　なると　おしりの　フックを　きの　えだに\nひっかけて　ぶらさがり　ねむりに　つく。\nねぞうが　わるいと　あさ　おっこちているよ。",
        "よるに　なると　おしりの　フックを　きの　えだに\nひっかけて　ぶらさがり　ねむりに　つく。\nねぞうが　わるいと　あさ　おっこちているよ。",
        "おなかが　へると　てあたりしだいに\nうごくものを　のみこんでは\nようかいえきで　とどめを　さす。",
        "おなかが　へると　てあたりしだいに\nうごくものを　のみこんでは\nようかいえきで　とどめを　さす。"
    ],
    "height": 1.0,
    "id": 70,
    "image_url": "https://raw.githubusercontent.com/PokeAPI/sprites/master/sprites/pokemon/other/official-artwork/70.png",
    "name": "ウツドン",
    "types": [
        "くさ",
        "どく"
    ],
    "weight": 6.4
}