{
    "descriptions": [
        "ダンスが　とくいで　おどりながら\nつぎつぎに　みずの　バルーンを\nつくりだし　てきに　ぶつけるぞ。",
        "なかまを　おもう　きもちが　つよい。\nトレーナーが　おちこんでいると\nダンスを　おどって　はげまそうとする。",
        "しらないダンスを　みると　こうふん。\nおどれるように　なるまで　けんめいに\nれんしゅうする　どりょくか　だよ。",
        "ふくらませた　みずのバルーンを\nてあしで　はじき　てきに　たたきつけ\nばくはつさせて　こうげき　するのだ。",
        "ダンスの　ステップで　てきの　わざを\nかわしながら　バルーンを　つぎつぎと\nつくって　こうげきを　たたみかける。",
        "なみの　おだやかな　よるになると\nリーダーの　アシレーヌの　うたごえに\nあわせて　なかまたちと　おどる。"
    ],
    "height": 0.6,
    "id": 729,
    "image_url": "https://raw.githubusercontent.com/PokeAPI/sprites/master/sprites/pokemon/other/official-artwork/729.png",
    "name": "オシャマリ",
    "types": [
        "みず"
    ],
    "weight": 17.5
}