{
    "descriptions": [
        "和人非常親近的寶可夢。\n沒人理睬的話就會很寂寞，\n流著黏糊糊的眼淚鳴叫。",
        "如果因為牠性情溫順\n就去戲弄牠，會被牠用角狠戳，\n再用粗粗的尾巴掃倒。",
        "和人非常親近。變得親密後，\n會用沾滿黏糊糊黏液的身體\n抱上來，這時就只能忍耐了。",
        "黏糊糊的皮膚下面\n有很厚的脂肪層，\n讓敵人的攻擊起不了作用。",
        "有時會因為無法理解\n訓練家的指令而目瞪口呆。\n那可愛的舉止讓牠深受歡迎。",
        "用伸長角產生的力道來\n攻擊對手，產生的威力比\n重量級拳擊手的拳擊還強１００倍。"
    ],
    "height": 2.0,
    "image_url": "https://raw.githubusercontent.com/PokeAPI/sprites/master/sprites/pokemon/other/official-artwork/706.png",
    "name": "黏美龍",
    "types": [
        "龍"
    ],
    "weight": 150.5
}