{
    "descriptions": [
        "有毒的觸手通常有８０根。\n活得越久，觸手的數量就越少。",
        "罕見地大量出現時，\n周圍海域的魚寶可夢\n會一隻不剩地全部消失。",
        "會從紅色珠子中發出超音波，\n使獵物變得虛弱，\n然後用８０根觸手纏住獵物。",
        "透過讓紅色珠子發光來與\n夥伴交流。閃爍的光芒是\n用來通知警戒狀況的信號。",
        "能夠自由伸縮身上的80根觸手，\n纏住獵物並讓獵物中毒，\n使對手失去抵抗力。",
        "能夠自由伸縮身上的80根觸手，\n纏住獵物並讓獵物中毒，\n使對手失去抵抗力。",
        "當牠頭上紅色珠子的光芒\n變強時，就得提高警覺了。\n那是牠發射超音波的前兆。",
        "能夠自由伸縮身上的８０根觸手。\n會像撒網般張開觸手捕捉獵物，\n並用毒針注入劇毒。"
    ],
    "height": 1.6,
    "image_url": "https://raw.githubusercontent.com/PokeAPI/sprites/master/sprites/pokemon/other/official-artwork/73.png",
    "name": "毒刺水母",
    "types": [
        "水",
        "毒"
    ],
    "weight": 55.0
}