{
    "descriptions": [
        "在周圍到處散播\n一閃一閃發著光的孢子。\n看到這個光的都會陷入沉睡中。",
        "在白天會一邊睡覺一邊從樹根吸取養分。\n到了晚上醒來，出走尋找新的樹木。",
        "會向四周散佈發光的孢子。\n雖然危險，但在睡睡菇棲息的森林\n舉行的夜遊行程很受人們歡迎。",
        "喜歡陰暗潮濕的地方。\n到了夜裡，菇傘下塞得\n滿滿的孢子就會發光。",
        "頭上的蘑菇傘非常好吃，\n雖然會被森林中的寶可夢吃掉，\n但是過了一晚上就會再生。",
        "白天也生活在昏暗的森林裡。\n會一邊閃爍一邊散播發著光的孢子\n來讓敵人陷入沉睡。"
    ],
    "height": 0.2,
    "image_url": "https://raw.githubusercontent.com/PokeAPI/sprites/master/sprites/pokemon/other/official-artwork/755.png",
    "name": "睡睡菇",
    "types": [
        "草",
        "妖精"
    ],
    "weight": 1.5
}