{
    "descriptions": [
        "When this Pokémon detects danger, it will open up its crystalline petals and fire beams from its conical body.",
        "Glimmora’s petals are made of crystallized poison energy. It has recently become evident that these petals resemble Tera Jewels."
    ],
    "height": 1.5,
    "image_url": "https://raw.githubusercontent.com/PokeAPI/sprites/master/sprites/pokemon/other/official-artwork/970.png",
    "name": "Glimmora",
    "types": [
        "Rock",
        "Poison"
    ],
    "weight": 45.0
}