{
    "descriptions": [
        "Produce elettricità contraendo e rilassando i muscoli.\nQuando si sente minacciato si illumina.",
        "In caso di pericolo, la sua pelliccia si illumina. Il\nnemico rimane accecato e lui ne approfitta per fuggire.",
        "Produce elettricità contraendo e rilassando i muscoli.\nQuando si sente minacciato si illumina.",
        "In caso di pericolo, la sua pelliccia si illumina. Il nemico rimane\naccecato e lui ne approfitta per fuggire.",
        "Produce elettricità contraendo i muscoli.\nQuando è scosso da tremiti, è segno che\nne sta generando in notevole quantità.",
        "La sua pelliccia irradia luce per via\ndell’elettricità. Invia segnali ai suoi simili\nagitando la punta luminosa della coda."
    ],
    "height": 0.5,
    "image_url": "https://raw.githubusercontent.com/PokeAPI/sprites/master/sprites/pokemon/other/official-artwork/403.png",
    "name": "Shinx",
    "types": [
        "Elettro"
    ],
    "weight": 9.5
}