{
    "descriptions": [
        "Si serve delle foglie laterali come lame contro i\nnemici. Il fluido che secerne dalla bocca scioglie\nqualsiasi cosa.",
        "Sputa Velenpolvere per immobilizzare il nemico e poi\nlo finisce con il suo Acido.",
        "Weepinbell è dotato di un grande uncino posteriore.\nDi notte lo usa per appendersi a un ramo e mettersi a\ndormire. Talvolta, agitandosi nel sonno, si sveglia al suolo.",
        "Weepinbell è dotato di un grande uncino posteriore.\nDi notte lo usa per appendersi a un ramo e mettersi a\ndormire. Talvolta, agitandosi nel sonno, si sveglia al suolo.",
        "Quando è affamato divora qualsiasi cosa\ngli capiti a tiro e la scioglie con i suoi\npotenti acidi.",
        "Quando è affamato divora qualsiasi cosa\ngli capiti a tiro e la scioglie con i suoi\npotenti acidi."
    ],
    "height": 1.0,
    "image_url": "https://raw.githubusercontent.com/PokeAPI/sprites/master/sprites/pokemon/other/official-artwork/70.png",
    "name": "Weepinbell",
    "types": [
        "Erba",
        "Veleno"
    ],
    "weight": 6.4
}