{
    "descriptions": [
        "用心灵感应与伙伴交流。\n据说兼有植物与某种别的遗传基因。",
        "６只成为１只完整的宝可梦。\n经常被好胜蟹袭击，\n但是会使用念力击退对方。",
        "６只加在一起算１只。\n即便出于某些原因少了１只，\n到了次日清晨也一定会变回６只。",
        "即便大小相同，\n阿罗拉产的蛋蛋却很沉重。\n这是因为里面长得十分密实。",
        "每一个蛋都相互吸引着\n旋转。６个蛋凑不齐时\n它就无法保持平衡。",
        "每一个蛋都相互吸引着\n旋转。６个蛋凑不齐时\n它就无法保持平衡。",
        "别看它看上去像蛋，其实是\n如假包换的宝可梦。据说它会\n用心灵感应来和伙伴通讯。",
        "６只不在一起就不安心。\n哪怕只是少了１只，\n都会马上想要逃跑。"
    ],
    "height": 0.4,
    "id": 102,
    "image_url": "https://raw.githubusercontent.com/PokeAPI/sprites/master/sprites/pokemon/other/official-artwork/102.png",
    "name": "蛋蛋",
    "types": [
        "草",
        "超能力"
    ],
    "weight": 2.5
}