{
    "descriptions": [
        "凉飕飕的时候，全身就会\n晕染成鲜红色。那样子正如\n令人感觉到秋意的风景诗。",
        "狂热爱好金鱼王的训练家\n分为角的爱好者和鱼鳍的爱好者。\n相互之间的关系很差。",
        "头上的角会像钻头一样旋转，\n即便是坚硬的岩石也能一下子贯穿。\n雄性有着鲜艳的颜色。",
        "雄性会在河底跳舞并以此来吸引雌性。\n雌性会聚集到跳得最美的雄性身边。",
        "雄性的职责是\n用头上的角打穿\n河里的石头筑巢。",
        "雄性的职责是\n用头上的角打穿\n河里的石头筑巢。",
        "到了秋天，体内的脂肪\n会因为要去求偶而增加，\n颜色也会变得非常漂亮。",
        "金鱼王之所以会用角挖穿\n河底的岩石来筑巢，是为了\n防止产下的卵被水流冲走。"
    ],
    "height": 1.3,
    "id": 119,
    "image_url": "https://raw.githubusercontent.com/PokeAPI/sprites/master/sprites/pokemon/other/official-artwork/119.png",
    "name": "金鱼王",
    "types": [
        "水"
    ],
    "weight": 39.0
}