{
    "descriptions": [
        "在流星闪耀的深夜里\n凝望着天空的样子，\n似乎是在怀念故乡。",
        "从它的轮廓判断，\n被认为是星星的转世。\n不知为何很喜欢小陨星。",
        "在流星众多的晚上，它们会聚集起来\n并围成一圈跳舞．如果能在那时\n看到它们，就会遇到一些好事情哦。",
        "据说是乘着流星而来。\n皮宝宝好像会出现在\n以前有陨石坠落过的地方。",
        "根据当地的传说，\n皮宝宝经常出没的地方\n就是流星陨落之处。",
        "有着星星一样的轮廓。\n由于那外形，人们相信\n它是乘着流星而来的。"
    ],
    "height": 0.3,
    "image_url": "https://raw.githubusercontent.com/PokeAPI/sprites/master/sprites/pokemon/other/official-artwork/173.png",
    "name": "皮宝宝",
    "types": [
        "妖精"
    ],
    "weight": 3.0
}