{
    "descriptions": [
        "找到伙伴后就会贴上去。\n贴得太多的话，\n有时候看上去就像积雨云。",
        "使用木棉球吐出的棉花\n制作而成的枕头和被褥\n是又轻又透气的高级商品。",
        "会喷出棉花保护身体。\n如果淋到雨，棉花就会受潮变重，\n身体变得动弹不得。",
        "一旦被袭击，就会喷出\n身上的棉花来代替自己的身体。\n喷出的棉花很快又会长出来。",
        "会喷出棉花保护身体。\n有时会被台风吹到\n地球的另一边。",
        "将木棉球和白蓬蓬的棉花\n混合后编织出的布料极其精致，\n因此常被高级品牌选用。"
    ],
    "height": 0.3,
    "image_url": "https://raw.githubusercontent.com/PokeAPI/sprites/master/sprites/pokemon/other/official-artwork/546.png",
    "name": "木棉球",
    "types": [
        "草",
        "妖精"
    ],
    "weight": 0.6
}