{
    "descriptions": [
        "从冰柱中诞生的宝可梦。\n用冰冷的气息制造雪的结晶，\n让天上下雪。",
        "抱紧的话，就会感觉凉凉的\n非常舒服。在炎热地区，\n是每家必备１只的便利宝可梦。",
        "会吐出零下５０度的冷气。\n如果呆在温暖的场所，\n就会一点点地变小。",
        "是由沐浴在朝阳下但仍不愿\n融化的冰柱诞生而成。\n晚上会潜入雪中睡觉。",
        "无法在炎热的地方生存。\n会吐出冷气来降雪，\n然后窝在积雪里睡觉。",
        "据说它是从冰柱中诞生的。\n为了能让自己生活得更舒适，\n会吐出零下５０度的冷气冻住四周。"
    ],
    "height": 0.4,
    "id": 582,
    "image_url": "https://raw.githubusercontent.com/PokeAPI/sprites/master/sprites/pokemon/other/official-artwork/582.png",
    "name": "迷你冰",
    "types": [
        "冰"
    ],
    "weight": 5.7
}