{
    "descriptions": [
        "Da es selbst die leisesten Gedanken seines\nGegners lesen kann, kann es immer zuerst angreifen.",
        "Es kämpft, indem es die Schwerter an seinen Ellbogen\nverlängert. Es ist ein Meister des Kampfes.",
        "Da es selbst die leisesten Gedanken seines Gegners lesen\nkann, kann es immer zuerst angreifen.",
        "Es kämpft, indem es die Schwerter an seinen Ellbogen\nverlängert. Es ist ein Meister des Kampfes.",
        "Dieses Pokémon wird als Krieger angesehen.\nDie Klingen an seinen Ellbogen benutzt es nur,\num etwas zu beschützen.",
        "Es spürt sofort, wenn jemand in Not ist, und eilt\nihm unverzüglich zu Hilfe."
    ],
    "height": 1.6,
    "image_url": "https://raw.githubusercontent.com/PokeAPI/sprites/master/sprites/pokemon/other/official-artwork/475.png",
    "name": "Galagladi",
    "types": [
        "Psycho",
        "Kampf"
    ],
    "weight": 52.0
}