{
    "descriptions": [
        "Sein Unterkörper ist in eine wolkenartige\nEnergieschicht gehüllt. Es jagt mit\nbis zu 300 km/h durch die Lüfte.",
        "Mit der Energie aus seiner Rute erzeugt es wilde\nStürme, die stark genug sind, um ganze Wohnhäuser\ndavonzuwehen.",
        "Sein Unterkörper ist in eine wolkenartige Energieschicht\ngehüllt. Es jagt mit bis zu 300 km/h durch die Lüfte.",
        "Mit der Energie aus seiner Rute erzeugt es wilde Stürme,\ndie stark genug sind, um ganze Wohnhäuser davonzuwehen."
    ],
    "height": 1.5,
    "image_url": "https://raw.githubusercontent.com/PokeAPI/sprites/master/sprites/pokemon/other/official-artwork/641.png",
    "name": "Boreos",
    "types": [
        "Flug"
    ],
    "weight": 63.0
}