{
    "descriptions": [
        "こはくに　残された　恐竜の\n遺伝子から　復活させた。\n高い　声で　鳴きながら　飛ぶ。",
        "甲高い　声で　叫びながら\n古代の　大空を　飛んでいたとされる\nどうもうな　ポケモン。",
        "コハクから　取り出した　遺伝子を　再生して\n復活した　恐竜　時代の　ポケモン。\n空の　王者だったと　想像されている。",
        "コハクから　取り出した　遺伝子を　再生して\n復活した　恐竜　時代の　ポケモン。\n空の　王者だったと　想像されている。",
        "恐竜　時代の　ポケモン。\nのこぎりのような　キバで　獲物を\n引き裂いて　喰っていた。",
        "古代の　大空の　王者。\n巨大　隕石の　落下で\n絶滅した　説が　根強い。",
        "琥珀に　残された　遺伝子から\n復元させた。　予想以上に\n凶暴で　犠牲者も　でた。",
        "古代の　大空を　我がもの顔で\n飛びまわっていた。　地面に　降りると\n歩くのも　遅く　弱かったらしい。",
        "コハクから　取り出された　遺伝子を\n研究して　復活させた\n大昔の　獰猛な　ポケモン。",
        "コハクから　取り出された　遺伝子を\n研究して　復活させた\n大昔の　獰猛な　ポケモン。",
        "古代の　獰猛な　ポケモン。\n完璧な　復元は\nいまの　科学でも　不可能らしい。",
        "のこぎりの　ような　キバは\nはがねポケモンの　皮膚さえ\nズタズタに　切り裂いてしまう。"
    ],
    "height": 1.8,
    "id": 142,
    "image_url": "https://raw.githubusercontent.com/PokeAPI/sprites/master/sprites/pokemon/other/official-artwork/142.png",
    "name": "プテラ",
    "types": [
        "いわ",
        "ひこう"
    ],
    "weight": 59.0
}