{
    "descriptions": [
        "大きな　体格で　空を　飛ぶ。\n地球を　約１６時間で\n１周してしまう。",
        "広い　海の　どこかに　住処が\nあると　言われている。難破した\n船を　陸まで　導いてくれる。",
        "１６時間で　地球を　１周できる。\n嵐で　難破しかけた　船を　見つけると\n陸地まで　誘導する　優しい　ポケモン。",
        "１６時間で　地球を　１周できる。\n嵐で　難破しかけた　船を　見つけると\n陸地まで　誘導する　優しい　ポケモン。",
        "遭難した　男が　助けられ\n連れて行かれた　孤島　は\nカイリューだけの　楽園だった。",
        "普段は　極めて　穏やかだが\nその　逆鱗に　触れると　すべてを\n壊し尽くすまで　収まらない。",
        "荒れ狂う　海も　ものともせずに\n飛んでいく。　その姿を　見かけた\n船長は　海の化身と　呼んだ。",
        "心　やさしい　ポケモンで　海で\n溺れた　人間や　ポケモンを\n助けたという　話を　よく聞く。",
        "広い　海の　どこかを　住みかにし\n飛んで　移動すると　言われているが\nあくまで　うわさに　過ぎない。",
        "広い　海の　どこかを　住みかにし\n飛んで　移動すると　言われているが\nあくまで　うわさに　過ぎない。",
        "溺れている　人や　ポケモンを\n見つけると　助けずには　いられない\n心優しい　ポケモン。",
        "海の　化身と　呼ばれる。\nカイリュー型の　彫像を\n舳先に　付ける　船も　多い。"
    ],
    "height": 2.2,
    "image_url": "https://raw.githubusercontent.com/PokeAPI/sprites/master/sprites/pokemon/other/official-artwork/149.png",
    "name": "カイリュー",
    "types": [
        "ドラゴン",
        "ひこう"
    ],
    "weight": 210.0
}