{
    "descriptions": [
        "両手と　お尻にある　３本の　毒針で\n相手を　刺して　刺して\n刺しまくって　攻撃する。",
        "集団で　現れることもある。\n猛スピードで　飛び回り\nお尻の　毒針で　刺しまくる。",
        "縄張り意識が　とても　強いので　スピアーの\nすみかには　近づかない　ほうが　身の　ためだ。\n怒ると　集団で　襲って　くるぞ。",
        "縄張り意識が　とても　強いので　スピアーの\nすみかには　近づかない　ほうが　身の　ためだ。\n怒ると　集団で　襲って　くるぞ。",
        "両手と　お尻にある　３本の\n毒バリで　相手を　刺して\n刺して　刺しまくって　攻撃する。",
        "両手と　お尻にある　３本の\n毒バリで　相手を　刺して\n刺して　刺しまくって　攻撃する。"
    ],
    "height": 1.0,
    "image_url": "https://raw.githubusercontent.com/PokeAPI/sprites/master/sprites/pokemon/other/official-artwork/15.png",
    "name": "スピアー",
    "types": [
        "むし",
        "どく"
    ],
    "weight": 29.5
}