{
    "descriptions": [
        "乾燥した　場所を　好む。\n目から　水を　出して\n体の　水分を　調節する。",
        "乾燥した　空気を　好む。\n水分を　調節　するときに\n出す　水が　涙に　見える。",
        "乾燥した　場所を　好む。\n目から　水を　出して\n体の　水分を　調節する。",
        "乾燥した　空気を　好む。\n水分を　調節　するときに\n出す　水が　涙に　見える。",
        "水が　苦手で　乾いた　場所に\n棲んでいる。　周りに　緑が\n少ないので　よく　目立つ。",
        "身体の　余計な　水分を　目から\n外に　出す。　その　成分は\n人間の　汗に　似ている。",
        "瞳から　水分を　放出。\n泣いているように　見えるので　敵を\n油断させる　効果も　あるらしい。",
        "あまり　身体が　湿りすぎると\n死んでしまうので　汗の　ように\n目から　水分を　出している。",
        "汗と　涙を　目から　流す。\n汗は　ちょっぴり　しょっぱくて\n涙は　ほんのり　苦い　味だ。",
        "乾燥した　岩場に　暮らす。\n緑の　玉は　乾くほど\nツヤツヤと　鈍く　輝く。"
    ],
    "height": 0.5,
    "image_url": "https://raw.githubusercontent.com/PokeAPI/sprites/master/sprites/pokemon/other/official-artwork/438.png",
    "name": "ウソハチ",
    "types": [
        "いわ"
    ],
    "weight": 15.0
}