{
    "descriptions": [
        "深い　海の　底で　暮らす。\n４枚の　ヒレの　模様を　光らせて\n獲物を　おびき寄せる。",
        "天敵に　見つからないように\n胸の　２枚の　ヒレを　使い\n海底を　這って　移動する。",
        "深い　海の　底で　暮らす。\n４枚の　ヒレの　模様を　光らせて\n獲物を　おびき寄せる。",
        "天敵に　見つからないように\n胸の　２枚の　ヒレを　使い\n海底を　這って　移動する。",
        "光で　獲物を　おびき寄せるが\n天敵である　獰猛な\nさかなポケモンまで　寄ってくるのだ。",
        "海底に　棲む　深海のポケモン。\nヒレを使い　海底を　はって\n好物の　スターミーを　探す。",
        "深い　海の　底は　獲物が\n少ない。　貴重な　エサを　巡り\nランターンと　激しく　争う。",
        "深海の　海底を　はうように\n泳ぐ。　幻想的な　ヒレの\n光は　夜空の　星の　よう。"
    ],
    "height": 1.2,
    "image_url": "https://raw.githubusercontent.com/PokeAPI/sprites/master/sprites/pokemon/other/official-artwork/457.png",
    "name": "ネオラント",
    "types": [
        "みず"
    ],
    "weight": 24.0
}