{
    "descriptions": [
        "人懐っこい　性格。美しい　さえずりと\n尾羽を　振る　動きで\n仲間に　合図を　送る。",
        "さえずる　声は　美しいが\n縄張りに　入った　相手は\n容赦しない　荒々しさだ。",
        "人懐っこい　性格。美しい　さえずりと\n尾羽を　振る　動きで\n仲間に　合図を　送る。",
        "さえずる　声は　美しいが\n縄張りに　入った　相手は\n容赦しない　荒々しさだ。",
        "人懐っこいので　扱いやすい\nポケモンだが　一度　戦いに\nなると　とても　荒々しいぞ。",
        "興奮　すると　体温が\n２倍まで　上がり　体内の\nホルモンが　活発に　なるのだ。",
        "人懐っこい　ポケモンだけど\n無理やり　触ると　身体を　一気に\n発熱させるので　火傷　するぞ。",
        "身体は　いつでも　暖かい。\n寒い　地域の　トレーナーは\nベッドで　一緒に　寝るらしい。",
        "美しい　さえずりは　威嚇。\n縄張りに　入った　ものは\n容赦なく　突きまくる。",
        "興奮すると　体温が\nグッと　上がる。　素手で　触ると\n火傷することも　あるほどだ。"
    ],
    "height": 0.3,
    "image_url": "https://raw.githubusercontent.com/PokeAPI/sprites/master/sprites/pokemon/other/official-artwork/661.png",
    "name": "ヤヤコマ",
    "types": [
        "ノーマル",
        "ひこう"
    ],
    "weight": 1.7
}