{
    "descriptions": [
        "鮮やかな　体色を　保つには\n非常に　手間が　かかるが　それを\n趣味にする　好事家も　いるのだ。",
        "鎌状の　花びらから　ビームを\n放つ。　分厚い　鉄板も\n真っ二つに　切断する　威力。",
        "むしポケモンの　ふりを　するのは\n身を　守るため。　両腕の\n花びらは　鋭い　切れ味。",
        "舞を　舞うように　敵を　切り裂く。\n雅な　姿　から　もっとも\n艶やかな　くさポケモンと　呼ばれる。",
        "美しい　花の　ポケモン。\nうまく　育った　ラランテスは\n素晴らしい　あざやかさを　もつ。",
        "両腕の　花びらは　薄く\n切れ味は　鋭い。　光を　集めて\nビームも　放てるぞ。"
    ],
    "height": 0.9,
    "id": 754,
    "image_url": "https://raw.githubusercontent.com/PokeAPI/sprites/master/sprites/pokemon/other/official-artwork/754.png",
    "name": "ラランテス",
    "types": [
        "くさ"
    ],
    "weight": 18.5
}